<?xml version="1.0" encoding="UTF-8"?>
<objects serializationModel="Studio.02.00.00">
	<object class="ParameterPreset" id="{b82f6070-2b1f-4607-ad64-f24caa065d07}">
		<property name="name">
			<value>Terrain</value>
		</property>
		<relationship name="folder">
			<destination>{eaeed16e-015f-4bc5-92aa-c79ba1458a97}</destination>
		</relationship>
		<relationship name="parameter">
			<destination>{56cfebb6-f692-4c19-8d2a-d69bcd062ac6}</destination>
		</relationship>
	</object>
	<object class="GameParameter" id="{56cfebb6-f692-4c19-8d2a-d69bcd062ac6}">
		<property name="parameterType">
			<value>2</value>
		</property>
		<property name="maximum">
			<value>4</value>
		</property>
		<property name="enumerationLabels">
			<value>Concrete</value>
			<value>Grass</value>
			<value>Thick Metal</value>
			<value>Thin Metal</value>
		</property>
		<property name="initialValue">
			<value>0</value>
		</property>
	</object>
</objects>
